stache_ai_s3vectors/__init__.py
stache_ai_s3vectors/provider.py
stache_ai_s3vectors-0.1.2.dist-info/METADATA
stache_ai_s3vectors-0.1.2.dist-info/WHEEL
stache_ai_s3vectors-0.1.2.dist-info/entry_points.txt
stache_ai_s3vectors-0.1.2.dist-info/top_level.txt
stache_ai_s3vectors-0.1.2.dist-info/RECORD
