Metadata-Version: 2.1
Name: stache-ai-s3vectors
Version: 0.1.2
Summary: S3Vectors provider for Stache AI
Author: Stache Contributors
License: MIT
Project-URL: Homepage, https://github.com/stache-ai/stache-ai
Project-URL: Repository, https://github.com/stache-ai/stache-ai
Keywords: stache,rag,ai,s3vectors
Classifier: Development Status :: 4 - Beta
Classifier: Intended Audience :: Developers
Classifier: Programming Language :: Python :: 3
Classifier: Programming Language :: Python :: 3.10
Classifier: Programming Language :: Python :: 3.11
Classifier: Programming Language :: Python :: 3.12
Requires-Python: >=3.10
Requires-Dist: stache-ai<1.0.0,>=0.1.0
Requires-Dist: boto3>=1.34.0
Provides-Extra: dev
Requires-Dist: pytest>=7.0.0; extra == "dev"
Requires-Dist: pytest-asyncio>=0.21.0; extra == "dev"
Requires-Dist: pytest-cov>=4.0.0; extra == "dev"
